README.txt
setup.py
adpil/__init__.py
adpil/adpil.py
adpil.egg-info/PKG-INFO
adpil.egg-info/SOURCES.txt
adpil.egg-info/dependency_links.txt
adpil.egg-info/top_level.txt