Metadata-Version: 1.1
Name: adpil
Version: 1.02
Summary: Interface between Adessowiki and PIL.Used by ia636 and ia870 toolboxes.
Home-page: https://github.com/robertoalotufo/adpil
Author: RCM
Author-email: rubens.campos.machado@gmail.com
License: BSD 3 clauses
Keywords: PIL
Platform: UNKNOWN
Classifier: Development Status :: 4 - Beta
Classifier: Intended Audience :: Science/Research
Classifier: Programming Language :: Python :: 2 :: Only
Classifier: Topic :: Scientific/Engineering :: Image Recognition
Classifier: License :: OSI Approved :: BSD License
